deformops/__init__.py
deformops/_build.py
deformops/_factors.py
deformops/benchmark.py
deformops/deform2d.py
deformops/deform2d.stb-backward.csv
deformops/deform2d.stb-forward.csv
deformops/deform2d_multiscale.py
deformops/deform2d_multiscale_fused.py
deformops/py.typed
deformops/include/deform2d.cpp
deformops/include/deform2d_multiscale.cpp
deformops/include/deform2d_multiscale_fused.cpp
deformops/include/cuda/deform2d.cu
deformops/include/cuda/deform2d_multiscale.cu
deformops/include/cuda/deform2d_multiscale_fused.cu
deformops/include/cuda/interpolate.cuh
deformops/include/cuda/utils.cuh
deformops/nn/__init__.py
deformops/nn/_sanitize.py
deformops/nn/conv.py
deformops/nn/msda.py
deformops-1.0.0.dist-info/LICENSE
deformops-1.0.0.dist-info/METADATA
deformops-1.0.0.dist-info/WHEEL
deformops-1.0.0.dist-info/top_level.txt
deformops-1.0.0.dist-info/RECORD
